py_dss_toolkit/__init__.py
py_dss_toolkit/algorithms/__init__.py
py_dss_toolkit/algorithms/LoadAllocation/__init__.py
py_dss_toolkit/algorithms/LoadAllocation/load_allocation.py
py_dss_toolkit/api/Creation.py
py_dss_toolkit/common/Enumerations.py
py_dss_toolkit/common/__init__.py
py_dss_toolkit/diagrams/ClassDiagram.puml
py_dss_toolkit/dss_tools/ConfigurationTools.py
py_dss_toolkit/dss_tools/DSSViewTools.py
py_dss_toolkit/dss_tools/SimulationTools.py
py_dss_toolkit/dss_tools/UtilitiesTools.py
py_dss_toolkit/dss_tools/__init__.py
py_dss_toolkit/dss_tools/dss_tools.py
py_dss_toolkit/model/BusesDataDF.py
py_dss_toolkit/model/ElementData.py
py_dss_toolkit/model/ElementDataDFs.py
py_dss_toolkit/model/ModelBase.py
py_dss_toolkit/model/ModelUtils.py
py_dss_toolkit/model/SegmentsDF.py
py_dss_toolkit/model/SummaryModelData.py
py_dss_toolkit/model/__init__.py
py_dss_toolkit/results/Results.py
py_dss_toolkit/results/__init__.py
py_dss_toolkit/results/ModelVerification/CapacitorControlVoltage.py
py_dss_toolkit/results/ModelVerification/Isolated.py
py_dss_toolkit/results/ModelVerification/LoadsTransformerVoltage.py
py_dss_toolkit/results/ModelVerification/ModelVerificationResults.py
py_dss_toolkit/results/ModelVerification/PDBusOder.py
py_dss_toolkit/results/ModelVerification/PhasesConnections.py
py_dss_toolkit/results/ModelVerification/PhasesConnections_PDelements.py
py_dss_toolkit/results/ModelVerification/RegulatorControlVoltage.py
py_dss_toolkit/results/ModelVerification/RegulatorkVA.py
py_dss_toolkit/results/ModelVerification/SameBus.py
py_dss_toolkit/results/ModelVerification/Summary.py
py_dss_toolkit/results/ModelVerification/TransformerData.py
py_dss_toolkit/results/ModelVerification/__init__.py
py_dss_toolkit/results/ShortCircuit/FaultResults.py
py_dss_toolkit/results/ShortCircuit/ShortCircuitCurrents.py
py_dss_toolkit/results/ShortCircuit/ShortCircuitImpedances.py
py_dss_toolkit/results/ShortCircuit/__init__.py
py_dss_toolkit-0.6.0.dist-info/licenses/AUTHORS.rst
py_dss_toolkit-0.6.0.dist-info/licenses/LICENSE
py_dss_toolkit-0.6.0.dist-info/METADATA
py_dss_toolkit-0.6.0.dist-info/WHEEL
py_dss_toolkit-0.6.0.dist-info/top_level.txt
py_dss_toolkit-0.6.0.dist-info/RECORD
